Metadata-Version: 2.1
Name: odoo13-addon-purchase_sale_inter_company
Version: 13.0.1.0.7
Summary: Intercompany PO/SO rules
Home-page: https://github.com/OCA/multi-company
Author: Odoo SA, Akretion, Tecnativa, Odoo Community Association (OCA)
Author-email: support@odoo-community.org
License: AGPL-3
Classifier: Programming Language :: Python
Classifier: Framework :: Odoo
Classifier: Framework :: Odoo :: 13.0
Classifier: License :: OSI Approved :: GNU Affero General Public License v3
Requires-Python: >=3.5
Requires-Dist: odoo13-addon-account-invoice-inter-company
Requires-Dist: odoo<13.1dev,>=13.0a
